<?xml version="1.0"?><import>
<!-- <import xmlns:xsi="http://www.w3.org/2001/XMLSchema-instance" xsi:noNamespaceSchemaLocation="http://www.guidewire.com/cc/import/cc_import.xsd">
-->

<!-- WC section start -->
<GlobalParameterExt public-id="lcc:218">
		<UserExt public-id="cc:10769"/> <!-- Stacey Kersten -->
		<LossTypeExt>AGRIWC</LossTypeExt>
		<FieldNameExt>ccliability</FieldNameExt>
		<GroupExt/>
		<ObjectTypeExt>user</ObjectTypeExt>
</GlobalParameterExt>
<GlobalParameterExt public-id="lcc:219">
		<UserExt public-id="cc:10769"/> <!-- Stacey Kersten -->
		<LossTypeExt>AGRIEL</LossTypeExt>
		<FieldNameExt>ccliability</FieldNameExt>
		<GroupExt/>
		<ObjectTypeExt>user</ObjectTypeExt>
</GlobalParameterExt>
<GlobalParameterExt public-id="lcc:220">
		<UserExt public-id="cc:10769"/> <!-- Stacey Kersten -->
		<LossTypeExt>ALTMARKETSWC</LossTypeExt>
		<FieldNameExt>ccliability</FieldNameExt>
		<GroupExt/>
		<ObjectTypeExt>user</ObjectTypeExt>
</GlobalParameterExt>
<GlobalParameterExt public-id="lcc:221">
		<UserExt public-id="cc:10769"/> <!-- Stacey Kersten -->
		<LossTypeExt>ALTMARKETSEL</LossTypeExt>
		<FieldNameExt>ccliability</FieldNameExt>
		<GroupExt/>
		<ObjectTypeExt>user</ObjectTypeExt>
</GlobalParameterExt>
<GlobalParameterExt public-id="lcc:222">
		<UserExt public-id="cc:10769"/> <!-- Stacey Kersten -->
		<LossTypeExt>ECUWC</LossTypeExt>
		<FieldNameExt>ccliability</FieldNameExt>
		<GroupExt/>
		<ObjectTypeExt>user</ObjectTypeExt>
</GlobalParameterExt>
<GlobalParameterExt public-id="lcc:223">
		<UserExt public-id="cc:10769"/> <!-- Stacey Kersten -->
		<LossTypeExt>ECUEL</LossTypeExt>
		<FieldNameExt>ccliability</FieldNameExt>
		<GroupExt/>
		<ObjectTypeExt>user</ObjectTypeExt>
</GlobalParameterExt>
<GlobalParameterExt public-id="lcc:224">
		<UserExt public-id="cc:10769"/> <!-- Stacey Kersten -->
		<LossTypeExt>OMWC</LossTypeExt>
		<FieldNameExt>ccliability</FieldNameExt>
		<GroupExt/>
		<ObjectTypeExt>user</ObjectTypeExt>
</GlobalParameterExt>
<GlobalParameterExt public-id="lcc:225">
		<UserExt public-id="cc:10769"/> <!-- Stacey Kersten -->
		<LossTypeExt>OMEL</LossTypeExt>
		<FieldNameExt>ccliability</FieldNameExt>
		<GroupExt/>
		<ObjectTypeExt>user</ObjectTypeExt>
</GlobalParameterExt>
<GlobalParameterExt public-id="lcc:157">
		<UserExt public-id="cc:10769"/> <!-- Stacey Kersten -->
		<LossTypeExt>PIMINMARINEWC</LossTypeExt>
		<FieldNameExt>ccliability</FieldNameExt>
		<GroupExt/>
		<ObjectTypeExt>user</ObjectTypeExt>
</GlobalParameterExt>
<GlobalParameterExt public-id="lcc:158">
		<UserExt public-id="cc:10769"/> <!-- Stacey Kersten -->
		<LossTypeExt>PIMINMARINEEL</LossTypeExt>
		<FieldNameExt>ccliability</FieldNameExt>
		<GroupExt/>
		<ObjectTypeExt>user</ObjectTypeExt>
</GlobalParameterExt>
<GlobalParameterExt public-id="lcc:159">
		<UserExt public-id="cc:10769"/> <!-- Stacey Kersten -->
		<LossTypeExt>SPECIALTYESWC</LossTypeExt>
		<FieldNameExt>ccliability</FieldNameExt>
		<GroupExt/>
		<ObjectTypeExt>user</ObjectTypeExt>
</GlobalParameterExt>
<GlobalParameterExt public-id="lcc:160">
		<UserExt public-id="cc:10769"/> <!-- Stacey Kersten -->
		<LossTypeExt>SPECIALTYESEL</LossTypeExt>
		<FieldNameExt>ccliability</FieldNameExt>
		<GroupExt/>
		<ObjectTypeExt>user</ObjectTypeExt>
</GlobalParameterExt>
<GlobalParameterExt public-id="lcc:161">
		<UserExt public-id="cc:10769"/> <!-- Stacey Kersten -->
		<LossTypeExt>STRATEGICCOMPWC</LossTypeExt>
		<FieldNameExt>ccliability</FieldNameExt>
		<GroupExt/>
		<ObjectTypeExt>user</ObjectTypeExt>
</GlobalParameterExt>
<GlobalParameterExt public-id="lcc:162">
		<UserExt public-id="cc:10769"/> <!-- Stacey Kersten -->
		<LossTypeExt>STRATEGICCOMPEL</LossTypeExt>
		<FieldNameExt>ccliability</FieldNameExt>
		<GroupExt/>
		<ObjectTypeExt>user</ObjectTypeExt>
</GlobalParameterExt>
<GlobalParameterExt public-id="lcc:163">
		<UserExt public-id="cc:10769"/> <!-- Stacey Kersten -->
		<LossTypeExt>truckingwc</LossTypeExt>
		<FieldNameExt>ccliability</FieldNameExt>
		<GroupExt/>
		<ObjectTypeExt>user</ObjectTypeExt>
</GlobalParameterExt>
<GlobalParameterExt public-id="lcc:164">
		<UserExt public-id="cc:10769"/> <!-- Stacey Kersten -->
		<LossTypeExt>TRUCKINGEL</LossTypeExt>
		<FieldNameExt>ccliability</FieldNameExt>
		<GroupExt/>
		<ObjectTypeExt>user</ObjectTypeExt>
</GlobalParameterExt>
<GlobalParameterExt public-id="lcc:165">
		<UserExt public-id="user:10106"/> <!-- Janelle -->
		<LossTypeExt>AGRIWC</LossTypeExt>
		<FieldNameExt>defaultclaimassign</FieldNameExt>
		<GroupExt/>
		<ObjectTypeExt>user</ObjectTypeExt>
</GlobalParameterExt>
<GlobalParameterExt public-id="lcc:166">
		<UserExt public-id="user:10106"/> <!-- Janelle -->
		<LossTypeExt>AGRIEL</LossTypeExt>
		<FieldNameExt>defaultclaimassign</FieldNameExt>
		<GroupExt/>
		<ObjectTypeExt>user</ObjectTypeExt>
</GlobalParameterExt>
<GlobalParameterExt public-id="lcc:167">
		<UserExt public-id="user:11124"/> <!-- Cindy McMahon -->
		<LossTypeExt>ALTMARKETSWC</LossTypeExt>
		<FieldNameExt>defaultclaimassign</FieldNameExt>
		<GroupExt/>
		<ObjectTypeExt>user</ObjectTypeExt>
</GlobalParameterExt>
<GlobalParameterExt public-id="lcc:168">
		<UserExt public-id="user:11124"/> <!-- Cindy McMahon -->
		<LossTypeExt>ALTMARKETSEL</LossTypeExt>
		<FieldNameExt>defaultclaimassign</FieldNameExt>
		<GroupExt/>
		<ObjectTypeExt>user</ObjectTypeExt>
</GlobalParameterExt>
<GlobalParameterExt public-id="lcc:169">
		<UserExt public-id="user:11117"/> <!-- Tom Jabs -->
		<LossTypeExt>ECUWC</LossTypeExt>
		<FieldNameExt>defaultclaimassign</FieldNameExt>
		<GroupExt/>
		<ObjectTypeExt>user</ObjectTypeExt>
</GlobalParameterExt>
<GlobalParameterExt public-id="lcc:170">
		<UserExt public-id="user:11117"/> <!-- Tom Jabs -->
		<LossTypeExt>ECUEL</LossTypeExt>
		<FieldNameExt>defaultclaimassign</FieldNameExt>
		<GroupExt/>
		<ObjectTypeExt>user</ObjectTypeExt>
</GlobalParameterExt>
<GlobalParameterExt public-id="lcc:171">
		<UserExt public-id="user:90040"/>   
		<LossTypeExt>OMWC</LossTypeExt>
		<FieldNameExt>defaultclaimassign</FieldNameExt>
		<GroupExt/>
		<ObjectTypeExt>user</ObjectTypeExt>
</GlobalParameterExt>
<GlobalParameterExt public-id="lcc:172">
		<UserExt public-id="user:90040"/>   
		<LossTypeExt>OMEL</LossTypeExt>
		<FieldNameExt>defaultclaimassign</FieldNameExt>
		<GroupExt/>
		<ObjectTypeExt>user</ObjectTypeExt>
</GlobalParameterExt>
<GlobalParameterExt public-id="lcc:173">
		<UserExt public-id="user:20005"/> <!-- Jane Eaton -->
		<LossTypeExt>PIMINMARINEWC</LossTypeExt>
		<FieldNameExt>defaultclaimassign</FieldNameExt>
		<GroupExt/>
		<ObjectTypeExt>user</ObjectTypeExt>
</GlobalParameterExt>
<GlobalParameterExt public-id="lcc:174">
		<UserExt public-id="user:20005"/> <!-- Jane Eaton -->
		<LossTypeExt>PIMINMARINEEL</LossTypeExt>
		<FieldNameExt>defaultclaimassign</FieldNameExt>
		<GroupExt/>
		<ObjectTypeExt>user</ObjectTypeExt>
</GlobalParameterExt>
<GlobalParameterExt public-id="lcc:175">
		<UserExt public-id="cc:9966"/>  <!-- Brian DeSoto -->
		<LossTypeExt>SPECIALTYESWC</LossTypeExt>
		<FieldNameExt>defaultclaimassign</FieldNameExt>
		<GroupExt/>
		<ObjectTypeExt>user</ObjectTypeExt>
</GlobalParameterExt>
<GlobalParameterExt public-id="lcc:176">
		<UserExt public-id="cc:9966"/>  <!-- Brian DeSoto -->
		<LossTypeExt>SPECIALTYESEL</LossTypeExt>
		<FieldNameExt>defaultclaimassign</FieldNameExt>
		<GroupExt/>
		<ObjectTypeExt>user</ObjectTypeExt>
</GlobalParameterExt>
<GlobalParameterExt public-id="lcc:177">
		<UserExt public-id="user:11196"/> <!-- Maria Hollis -->
		<LossTypeExt>STRATEGICCOMPWC</LossTypeExt>
		<FieldNameExt>defaultclaimassign</FieldNameExt>
		<GroupExt/>
		<ObjectTypeExt>user</ObjectTypeExt>
</GlobalParameterExt>
<GlobalParameterExt public-id="lcc:178">
		<UserExt public-id="user:11196"/> <!-- Maia Hollis -->
		<LossTypeExt>STRATEGICCOMPEL</LossTypeExt>
		<FieldNameExt>defaultclaimassign</FieldNameExt>
		<GroupExt/>
		<ObjectTypeExt>user</ObjectTypeExt>
</GlobalParameterExt>
<GlobalParameterExt public-id="lcc:179">
		<UserExt public-id="user:11299"/> <!-- Angie Wilson-Travis -->
		<LossTypeExt>truckingwc</LossTypeExt>
		<FieldNameExt>defaultclaimassign</FieldNameExt>
		<GroupExt/>
		<ObjectTypeExt>user</ObjectTypeExt>
</GlobalParameterExt>
<GlobalParameterExt public-id="lcc:180">
		<UserExt public-id="user:11299"/> <!-- Angie Wilson-Travis -->
		<LossTypeExt>TRUCKINGEL</LossTypeExt>
		<FieldNameExt>defaultclaimassign</FieldNameExt>
		<GroupExt/>
		<ObjectTypeExt>user</ObjectTypeExt>
</GlobalParameterExt>
<GlobalParameterExt public-id="lcc:181">
		<UserExt public-id="user:10106"/> <!-- Janelle -->
		<LossTypeExt>AGRIWC</LossTypeExt>
		<FieldNameExt>incidentassign</FieldNameExt>
		<GroupExt/>
		<ObjectTypeExt>user</ObjectTypeExt>
</GlobalParameterExt>
<GlobalParameterExt public-id="lcc:182">
		<UserExt public-id="user:10106"/> <!-- Janelle -->
		<LossTypeExt>AGRIEL</LossTypeExt>
		<FieldNameExt>incidentassign</FieldNameExt>
		<GroupExt/>
		<ObjectTypeExt>user</ObjectTypeExt>
</GlobalParameterExt>
<GlobalParameterExt public-id="lcc:183">
		<UserExt public-id="user:11137"/> <!-- Michele Riley -->
		<LossTypeExt>ALTMARKETSWC</LossTypeExt>
		<FieldNameExt>incidentassign</FieldNameExt>
		<GroupExt/>
		<ObjectTypeExt>user</ObjectTypeExt>
</GlobalParameterExt>
<GlobalParameterExt public-id="lcc:184">
		<UserExt public-id="user:11137"/> <!-- Michele Riley -->
		<LossTypeExt>ALTMARKETSEL</LossTypeExt>
		<FieldNameExt>incidentassign</FieldNameExt>
		<GroupExt/>
		<ObjectTypeExt>user</ObjectTypeExt>
</GlobalParameterExt>
<GlobalParameterExt public-id="lcc:185">
		<UserExt public-id="user:11117"/> <!-- Tom Jabs -->
		<LossTypeExt>ECUWC</LossTypeExt>
		<FieldNameExt>incidentassign</FieldNameExt>
		<GroupExt/>
		<ObjectTypeExt>user</ObjectTypeExt>
</GlobalParameterExt>
<GlobalParameterExt public-id="lcc:186">
		<UserExt public-id="user:11117"/> <!-- Tom Jabs -->
		<LossTypeExt>ECUEL</LossTypeExt>
		<FieldNameExt>incidentassign</FieldNameExt>
		<GroupExt/>
		<ObjectTypeExt>user</ObjectTypeExt>
</GlobalParameterExt>
<GlobalParameterExt public-id="lcc:187">
		<UserExt public-id="user:90040"/>   
		<LossTypeExt>OMWC</LossTypeExt>
		<FieldNameExt>incidentassign</FieldNameExt>
		<GroupExt/>
		<ObjectTypeExt>user</ObjectTypeExt>
</GlobalParameterExt>
<GlobalParameterExt public-id="lcc:188">
		<UserExt public-id="user:90040"/>   
		<LossTypeExt>OMEL</LossTypeExt>
		<FieldNameExt>incidentassign</FieldNameExt>
		<GroupExt/>
		<ObjectTypeExt>user</ObjectTypeExt>
</GlobalParameterExt>
<GlobalParameterExt public-id="lcc:189">
		<UserExt public-id="user:20005"/> <!-- Jane Eaton -->
		<LossTypeExt>PIMINMARINEWC</LossTypeExt>
		<FieldNameExt>incidentassign</FieldNameExt>
		<GroupExt/>
		<ObjectTypeExt>user</ObjectTypeExt>
</GlobalParameterExt>
<GlobalParameterExt public-id="lcc:190">
		<UserExt public-id="user:20005"/> <!-- Jane Eaton -->
		<LossTypeExt>PIMINMARINEEL</LossTypeExt>
		<FieldNameExt>incidentassign</FieldNameExt>
		<GroupExt/>
		<ObjectTypeExt>user</ObjectTypeExt>
</GlobalParameterExt>
<GlobalParameterExt public-id="lcc:191">
		<UserExt public-id="cc:9966"/>  <!-- Brian DeSoto -->
		<LossTypeExt>SPECIALTYESWC</LossTypeExt>
		<FieldNameExt>incidentassign</FieldNameExt>
		<GroupExt/>
		<ObjectTypeExt>user</ObjectTypeExt>
</GlobalParameterExt>
<GlobalParameterExt public-id="lcc:192">
		<UserExt public-id="cc:9966"/>  <!-- Brian DeSoto -->
		<LossTypeExt>SPECIALTYESEL</LossTypeExt>
		<FieldNameExt>incidentassign</FieldNameExt>
		<GroupExt/>
		<ObjectTypeExt>user</ObjectTypeExt>
</GlobalParameterExt>
<GlobalParameterExt public-id="lcc:193">
		<UserExt public-id="user:11206"/> <!-- Sandra Laborde -->
		<LossTypeExt>STRATEGICCOMPWC</LossTypeExt>
		<FieldNameExt>incidentassign</FieldNameExt>
		<GroupExt/>
		<ObjectTypeExt>user</ObjectTypeExt>
</GlobalParameterExt>
<GlobalParameterExt public-id="lcc:194">
		<UserExt public-id="user:11206"/> <!-- Sandra Laborde -->
		<LossTypeExt>STRATEGICCOMPEL</LossTypeExt>
		<FieldNameExt>incidentassign</FieldNameExt>
		<GroupExt/>
		<ObjectTypeExt>user</ObjectTypeExt>
</GlobalParameterExt>
<GlobalParameterExt public-id="lcc:195">
		<UserExt public-id="user:11299"/> <!-- Angie Wilson-Travis -->
		<LossTypeExt>truckingwc</LossTypeExt>
		<FieldNameExt>incidentassign</FieldNameExt>
		<GroupExt/>
		<ObjectTypeExt>user</ObjectTypeExt>
</GlobalParameterExt>
<GlobalParameterExt public-id="lcc:196">
		<UserExt public-id="user:11299"/> <!-- Angie Wilson-Travis -->
		<LossTypeExt>TRUCKINGEL</LossTypeExt>
		<FieldNameExt>incidentassign</FieldNameExt>
		<GroupExt/>
		<ObjectTypeExt>user</ObjectTypeExt>
</GlobalParameterExt>
<GlobalParameterExt public-id="lcc:197">
		<UserExt public-id="user:10106"/> <!-- Janelle -->
		<LossTypeExt>AGRIWC</LossTypeExt>
		<FieldNameExt>unitmanager</FieldNameExt>
		<GroupExt/>
		<ObjectTypeExt>user</ObjectTypeExt>
</GlobalParameterExt>
<GlobalParameterExt public-id="lcc:198">
		<UserExt public-id="user:10106"/> <!-- Janelle -->
		<LossTypeExt>AGRIEL</LossTypeExt>
		<FieldNameExt>unitmanager</FieldNameExt>
		<GroupExt/>
		<ObjectTypeExt>user</ObjectTypeExt>
</GlobalParameterExt>
<GlobalParameterExt public-id="lcc:199">
		<UserExt public-id="user:11117"/> <!-- Tom Jabs -->
		<LossTypeExt>ALTMARKETSWC</LossTypeExt>
		<FieldNameExt>unitmanager</FieldNameExt>
		<GroupExt/>
		<ObjectTypeExt>user</ObjectTypeExt>
</GlobalParameterExt>
<GlobalParameterExt public-id="lcc:200">
		<UserExt public-id="user:11117"/> <!-- Tom Jabs -->
		<LossTypeExt>ALTMARKETSEL</LossTypeExt>
		<FieldNameExt>unitmanager</FieldNameExt>
		<GroupExt/>
		<ObjectTypeExt>user</ObjectTypeExt>
</GlobalParameterExt>
<GlobalParameterExt public-id="lcc:201">
		<UserExt public-id="user:80010"/>  <!-- Bob Burkholder -->
		<LossTypeExt>ECUWC</LossTypeExt>
		<FieldNameExt>unitmanager</FieldNameExt>
		<GroupExt/>
		<ObjectTypeExt>user</ObjectTypeExt>
</GlobalParameterExt>
<GlobalParameterExt public-id="lcc:202">
		<UserExt public-id="user:80010"/>  <!-- Bob Burkholder -->
		<LossTypeExt>ECUEL</LossTypeExt>
		<FieldNameExt>unitmanager</FieldNameExt>
		<GroupExt/>
		<ObjectTypeExt>user</ObjectTypeExt>
</GlobalParameterExt>
<GlobalParameterExt public-id="lcc:203">
		<UserExt public-id="user:90040"/>   
		<LossTypeExt>OMWC</LossTypeExt>
		<FieldNameExt>unitmanager</FieldNameExt>
		<GroupExt/>
		<ObjectTypeExt>user</ObjectTypeExt>
</GlobalParameterExt>
<GlobalParameterExt public-id="lcc:204">
		<UserExt public-id="user:90040"/>   
		<LossTypeExt>OMEL</LossTypeExt>
		<FieldNameExt>unitmanager</FieldNameExt>
		<GroupExt/>
		<ObjectTypeExt>user</ObjectTypeExt>
</GlobalParameterExt>
<GlobalParameterExt public-id="lcc:205">
		<UserExt public-id="user:20027"/> <!-- Josh Schaad-->
		<LossTypeExt>PIMINMARINEWC</LossTypeExt>
		<FieldNameExt>unitmanager</FieldNameExt>
		<GroupExt/>
		<ObjectTypeExt>user</ObjectTypeExt>
</GlobalParameterExt>
<GlobalParameterExt public-id="lcc:206">
		<UserExt public-id="user:20027"/> <!-- Josh Schaad-->
		<LossTypeExt>PIMINMARINEEL</LossTypeExt>
		<FieldNameExt>unitmanager</FieldNameExt>
		<GroupExt/>
		<ObjectTypeExt>user</ObjectTypeExt>
</GlobalParameterExt>
<GlobalParameterExt public-id="lcc:207">
		<UserExt public-id="cc:9966"/>  <!-- Brian DeSoto -->
		<LossTypeExt>SPECIALTYESWC</LossTypeExt>
		<FieldNameExt>unitmanager</FieldNameExt>
		<GroupExt/>
		<ObjectTypeExt>user</ObjectTypeExt>
</GlobalParameterExt>
<GlobalParameterExt public-id="lcc:208">
		<UserExt public-id="cc:9966"/>  <!-- Brian DeSoto -->
		<LossTypeExt>SPECIALTYESEL</LossTypeExt>
		<FieldNameExt>unitmanager</FieldNameExt>
		<GroupExt/>
		<ObjectTypeExt>user</ObjectTypeExt>
</GlobalParameterExt>
<GlobalParameterExt public-id="lcc:209">
		<UserExt public-id="user:11224"/> <!-- Pauline -->
		<LossTypeExt>STRATEGICCOMPWC</LossTypeExt>
		<FieldNameExt>unitmanager</FieldNameExt>
		<GroupExt/>
		<ObjectTypeExt>user</ObjectTypeExt>
</GlobalParameterExt>
<GlobalParameterExt public-id="lcc:210">
		<UserExt public-id="user:11224"/> <!-- Pauline -->
		<LossTypeExt>STRATEGICCOMPEL</LossTypeExt>
		<FieldNameExt>unitmanager</FieldNameExt>
		<GroupExt/>
		<ObjectTypeExt>user</ObjectTypeExt>
</GlobalParameterExt>
<GlobalParameterExt public-id="lcc:211">
		<UserExt public-id="user:10078"/> <!-- William Riemen -->
		<LossTypeExt>truckingwc</LossTypeExt>
		<FieldNameExt>unitmanager</FieldNameExt>
		<GroupExt/>
		<ObjectTypeExt>user</ObjectTypeExt>
</GlobalParameterExt>
<GlobalParameterExt public-id="lcc:212">
		<UserExt public-id="user:10078"/> <!-- William Riemen -->
		<LossTypeExt>TRUCKINGEL</LossTypeExt>
		<FieldNameExt>unitmanager</FieldNameExt>
		<GroupExt/>
		<ObjectTypeExt>user</ObjectTypeExt>
</GlobalParameterExt>
<GlobalParameterExt public-id="lcc:214">
		<UserExt public-id="user:11124"/> <!-- Cindy McMahon -->
		<LossTypeExt></LossTypeExt>
		<FieldNameExt>mitchell_bi_approval</FieldNameExt>
		<GroupExt/>
		<ObjectTypeExt>user</ObjectTypeExt>
</GlobalParameterExt>
<GlobalParameterExt public-id="lcc:215">
		<UserExt public-id="user:11124"/> <!-- Cindy McMahon -->
		<LossTypeExt></LossTypeExt>
		<FieldNameExt>hcs_bi_approval</FieldNameExt>
		<GroupExt/>
		<ObjectTypeExt>user</ObjectTypeExt>
</GlobalParameterExt>
<GlobalParameterExt public-id="lcc:216">
		<UserExt public-id="user:11124"/> <!-- Cindy McMahon -->
		<LossTypeExt></LossTypeExt>
		<FieldNameExt>occm_bi_approval</FieldNameExt>
		<GroupExt/>
		<ObjectTypeExt>user</ObjectTypeExt>
</GlobalParameterExt>
<GlobalParameterExt public-id="lcc:217">  
		<UserExt public-id="user:11117"/> <!-- Tom Jabs -->
		<LossTypeExt></LossTypeExt>
		<FieldNameExt>defaultcorpaccount</FieldNameExt>
		<GroupExt/>
		<ObjectTypeExt>user</ObjectTypeExt>
	</GlobalParameterExt>
<!-- WC section end -->
</import>
